fastarray/__init__.py
fastarray/backend.py
fastarray/compression.py
fastarray/fastarray.py
fastarray/index.py
fastarray/jax_fastarray.py
fastarray/jax_integration.py
fastarray/jax_training_integration.py
fastarray/linalg.py
fastarray/memory.py
fastarray/numpy_api.py
fastarray/random.py
fastarray_tpu-1.0.0.dist-info/METADATA
fastarray_tpu-1.0.0.dist-info/WHEEL
fastarray_tpu-1.0.0.dist-info/top_level.txt
fastarray_tpu-1.0.0.dist-info/RECORD
