Metadata-Version: 2.4
Name: FastArray-TPU
Version: 1.0.0
Summary: Advanced compressed array library with extreme TPU-optimized compression and multi-device support - drop-in replacement for NumPy
Home-page: https://github.com/fastarray/fastarray
Author: FastArray Development Team
Author-email: FastArray Development Team <fastarray@example.com>
License: MIT
Project-URL: Homepage, https://github.com/fastarray/fastarray
Project-URL: Repository, https://github.com/fastarray/fastarray
Project-URL: Bug Reports, https://github.com/fastarray/fastarray/issues
Project-URL: Documentation, https://fastarray.readthedocs.io/
Project-URL: TPU Optimization Guide, https://github.com/fastarray/fastarray/blob/main/TPU_GUIDE.md
Classifier: Development Status :: 5 - Production/Stable
Classifier: Intended Audience :: Developers
Classifier: Intended Audience :: Science/Research
Classifier: License :: OSI Approved :: MIT License
Classifier: Operating System :: OS Independent
Classifier: Programming Language :: Python :: 3
Classifier: Programming Language :: Python :: 3.8
Classifier: Programming Language :: Python :: 3.9
Classifier: Programming Language :: Python :: 3.10
Classifier: Programming Language :: Python :: 3.11
Classifier: Programming Language :: Python :: 3.12
Classifier: Topic :: Scientific/Engineering
Classifier: Topic :: Scientific/Engineering :: Mathematics
Classifier: Topic :: Software Development
Classifier: Topic :: Software Development :: Libraries
Classifier: Topic :: Software Development :: Libraries :: Python Modules
Classifier: Topic :: Utilities
Requires-Python: >=3.8
Requires-Dist: numpy>=1.21.0
Requires-Dist: blosc>=1.0.0; platform_python_implementation != "PyPy"
Provides-Extra: dev
Requires-Dist: pytest>=6.0; extra == "dev"
Requires-Dist: pytest-cov>=2.0; extra == "dev"
Requires-Dist: mypy>=0.910; extra == "dev"
Requires-Dist: black>=21.0; extra == "dev"
Requires-Dist: flake8>=3.8; extra == "dev"
Provides-Extra: jax
Requires-Dist: jax>=0.4.0; extra == "jax"
Requires-Dist: jaxlib>=0.4.0; extra == "jax"
Requires-Dist: flax>=0.7.0; extra == "jax"
Requires-Dist: optax>=0.1.0; extra == "jax"
Provides-Extra: pytorch
Requires-Dist: torch>=1.9.0; extra == "pytorch"
Provides-Extra: scipy
Requires-Dist: scipy>=1.7.0; extra == "scipy"
Provides-Extra: full
Requires-Dist: jax>=0.4.0; extra == "full"
Requires-Dist: jaxlib>=0.4.0; extra == "full"
Requires-Dist: flax>=0.7.0; extra == "full"
Requires-Dist: optax>=0.1.0; extra == "full"
Requires-Dist: torch>=1.9.0; extra == "full"
Requires-Dist: scipy>=1.7.0; extra == "full"
Dynamic: author
Dynamic: home-page
Dynamic: requires-python
